stretchable-1.1.7.dist-info/METADATA
stretchable-1.1.7.dist-info/WHEEL
stretchable-1.1.7.dist-info/licenses/LICENSE
stretchable/context.py
stretchable/core.py
stretchable/exceptions.py
stretchable/node.py
stretchable/style/core.py
stretchable/style/geometry/length.py
stretchable/style/geometry/rect.py
stretchable/style/geometry/size.py
stretchable/style/geometry/__init__.py
stretchable/style/props.py
stretchable/style/__init__.py
stretchable/__init__.py
stretchable/taffylib.pyd
stretchable-1.1.7.dist-info/RECORD
