Metadata-Version: 2.4
Name: stretchable
Version: 1.1.7
Classifier: Development Status :: 5 - Production/Stable
Classifier: License :: OSI Approved :: MIT License
Classifier: Intended Audience :: Developers
Classifier: Programming Language :: Python :: 3.8
Classifier: Programming Language :: Python :: 3.9
Classifier: Programming Language :: Python :: 3.10
Classifier: Programming Language :: Python :: 3.11
Classifier: Programming Language :: Python :: 3.12
Classifier: Programming Language :: Python :: 3.13
Classifier: Programming Language :: Rust
Classifier: Programming Language :: Python :: Implementation :: CPython
Classifier: Programming Language :: Python :: Implementation :: PyPy
Classifier: Operating System :: OS Independent
Classifier: Typing :: Typed
Requires-Dist: attrs >=23.1, <26.0
Requires-Dist: maturin ==1.7.6 ; extra == 'build'
Requires-Dist: build ; extra == 'build'
Requires-Dist: twine ; extra == 'build'
Requires-Dist: pytest ; extra == 'test'
Requires-Dist: pytest-cache ; extra == 'test'
Requires-Dist: pytest-cov ; extra == 'test'
Requires-Dist: pytest-html ; extra == 'test'
Requires-Dist: hypothesis ; extra == 'test'
Requires-Dist: selenium ; extra == 'test'
Requires-Dist: sphinx ; extra == 'docs'
Requires-Dist: myst-parser ; extra == 'docs'
Requires-Dist: furo ; extra == 'docs'
Requires-Dist: sphinx-copybutton ; extra == 'docs'
Requires-Dist: sphinx-autobuild ; extra == 'docs'
Requires-Dist: sphinx-autodoc-typehints ; extra == 'docs'
Requires-Dist: sphinx-design >=0.5, <1.0 ; extra == 'docs'
Requires-Dist: sphinxcontrib-mermaid >=0.9.2, <1.0 ; extra == 'docs'
Provides-Extra: build
Provides-Extra: test
Provides-Extra: docs
License-File: LICENSE
Summary: Layout library for Python (based on Taffy, a rust-powered implementation of CSS Grid/Flexbox)
Keywords: flexbox,grid,block,stretch,css,layout
Author: Kenneth Trelborg Vestergaard
Requires-Python: >=3.8
Project-URL: Homepage, https://stretchable.readthedocs.io/en/latest/
Project-URL: Documentation, https://stretchable.readthedocs.io/en/latest/
Project-URL: Source, https://github.com/mortencombat/stretchable
Project-URL: Tracker, https://github.com/mortencombat/stretchable/issues
